experiment_phase/__init__.py
experiment_phase/data_prepare.py
experiment_phase/make_dataset_model.py
experiment_phase/predict.py
experiment_phase/training_model.py
experiment_phase-0.1.4.dist-info/METADATA
experiment_phase-0.1.4.dist-info/WHEEL
experiment_phase-0.1.4.dist-info/RECORD
