Metadata-Version: 2.1
Name: experiment_phase
Version: 0.1.4
Summary: Experimentation
Home-page: https://github.com/ananyanaik22/app_1.git
License: MIT
Author: Prabhakar Ananya
Author-email: pananya21t@gmail.com
Requires-Python: >=3.9
Classifier: License :: OSI Approved :: MIT License
Classifier: Programming Language :: Python :: 3
Classifier: Programming Language :: Python :: 3.9
Classifier: Programming Language :: Python :: 3.10
Classifier: Programming Language :: Python :: 3.11
Classifier: Programming Language :: Python :: 3.12
Requires-Dist: numpy (>=2.1.1)
Requires-Dist: pandas (==2.2.2)
Requires-Dist: scikit-learn (==1.5.2)
Project-URL: Repository, https://github.com/ananyanaik22/app_1.git
